pytest_adaptavist/__init__.py
pytest_adaptavist/_atm_configuration.py
pytest_adaptavist/_helpers.py
pytest_adaptavist/_pytest_adaptavist.py
pytest_adaptavist/_xdist.py
pytest_adaptavist/constants.py
pytest_adaptavist/metablock.py
pytest_adaptavist/py.typed
pytest_adaptavist/types.py
pytest_adaptavist-5.8.0.dist-info/LICENSE.md
pytest_adaptavist-5.8.0.dist-info/METADATA
pytest_adaptavist-5.8.0.dist-info/WHEEL
pytest_adaptavist-5.8.0.dist-info/entry_points.txt
pytest_adaptavist-5.8.0.dist-info/top_level.txt
pytest_adaptavist-5.8.0.dist-info/RECORD
