Metadata-Version: 2.1
Name: pytest-adaptavist
Version: 5.8.0
Summary: pytest plugin for generating test execution results within Jira Test Management (tm4j)
Home-page: https://github.com/devolo/pytest-adaptavist
Author: Stephan Steinberg, Markus Bong, Guido Schmitz
Author-email: markus.bong@devolo.de, guido.schmitz@devolo.de
License: MIT
Keywords: python pytest adaptavist kanoah tm4j jira test testmanagement report
Platform: any
Classifier: Framework :: Pytest
Classifier: Intended Audience :: Developers
Classifier: License :: OSI Approved :: MIT License
Classifier: Operating System :: OS Independent
Classifier: Programming Language :: Python
Classifier: Programming Language :: Python :: 3
Classifier: Topic :: Software Development :: Quality Assurance
Classifier: Topic :: Software Development :: Testing
Classifier: Topic :: Utilities
Classifier: Topic :: Software Development :: Libraries :: Python Modules
Requires-Python: >=3.8
License-File: LICENSE.md
Requires-Dist: adaptavist (>=2.1.0)
Requires-Dist: pytest (>=5.4.0)
Requires-Dist: pytest-assume (>=2.3.2)
Requires-Dist: pytest-metadata (>=1.6.0)
Provides-Extra: test
Requires-Dist: beautifulsoup4 ; extra == 'test'
Requires-Dist: lxml ; extra == 'test'
Requires-Dist: requests ; extra == 'test'
